{
  "updated": "2026-06-29 17:52 HKT",
  "tickers": {
    "NVDY": {
      "name": "YieldMax NVDA 期權收益 ETF",
      "name_en": "YieldMax NVDA Option Income",
      "market": "US",
      "currency": "USD",
      "series": "YieldMax",
      "tax_note": "ROC，通常豁免預扣稅",
      "price": 12.03,
      "price_1y_ago": 9.7847,
      "price_chg_1y": 0.2295,
      "freq": "weekly",
      "freq_cn": "週息",
      "divs_per_year": 52,
      "recent_div": 0.101,
      "total_div_1y": 8.178,
      "annual_yield": 0.6798,
      "net_1y": 0.9093,
      "health": "green"
    },
    "TSLY": {
      "name": "YieldMax TSLA 期權收益 ETF",
      "name_en": "YieldMax TSLA Option Income",
      "market": "US",
      "currency": "USD",
      "series": "YieldMax",
      "tax_note": "ROC，通常豁免預扣稅",
      "price": 26.45,
      "price_1y_ago": 21.5016,
      "price_chg_1y": 0.2301,
      "freq": "weekly",
      "freq_cn": "週息",
      "divs_per_year": 52,
      "recent_div": 0.267,
      "total_div_1y": 24.457,
      "annual_yield": 0.9247,
      "net_1y": 1.1548,
      "health": "green"
    },
    "MSFO": {
      "name": "YieldMax MSFT 期權收益 ETF",
      "name_en": "YieldMax MSFT Option Income",
      "market": "US",
      "currency": "USD",
      "series": "YieldMax",
      "tax_note": "ROC，通常豁免預扣稅",
      "price": 10.46,
      "price_1y_ago": NaN,
      "price_chg_1y": NaN,
      "freq": "weekly",
      "freq_cn": "週息",
      "divs_per_year": 52,
      "recent_div": 0.056,
      "total_div_1y": 4.485,
      "annual_yield": 0.4288,
      "net_1y": NaN,
      "health": "red"
    },
    "CONY": {
      "name": "YieldMax COIN 期權收益 ETF",
      "name_en": "YieldMax COIN Option Income",
      "market": "US",
      "currency": "USD",
      "series": "YieldMax",
      "tax_note": "ROC，通常豁免預扣稅",
      "price": 19.18,
      "price_1y_ago": NaN,
      "price_chg_1y": NaN,
      "freq": "weekly",
      "freq_cn": "週息",
      "divs_per_year": 52,
      "recent_div": 0.26,
      "total_div_1y": 37.039,
      "annual_yield": 1.9311,
      "net_1y": NaN,
      "health": "red"
    },
    "PLTY": {
      "name": "YieldMax PLTR 期權收益 ETF",
      "name_en": "YieldMax PLTR Option Income",
      "market": "US",
      "currency": "USD",
      "series": "YieldMax",
      "tax_note": "ROC，通常豁免預扣稅",
      "price": 27.45,
      "price_1y_ago": 31.3325,
      "price_chg_1y": -0.1239,
      "freq": "weekly",
      "freq_cn": "週息",
      "divs_per_year": 52,
      "recent_div": 0.261,
      "total_div_1y": 36.15,
      "annual_yield": 1.3169,
      "net_1y": 1.193,
      "health": "green"
    },
    "MSTY": {
      "name": "YieldMax MSTR 期權收益 ETF",
      "name_en": "YieldMax MSTR Option Income",
      "market": "US",
      "currency": "USD",
      "series": "YieldMax",
      "tax_note": "ROC，通常豁免預扣稅",
      "price": 11.53,
      "price_1y_ago": 45.1037,
      "price_chg_1y": -0.7444,
      "freq": "weekly",
      "freq_cn": "週息",
      "divs_per_year": 52,
      "recent_div": 0.188,
      "total_div_1y": 42.217,
      "annual_yield": 3.6615,
      "net_1y": 2.9171,
      "health": "green"
    },
    "YMAX": {
      "name": "YieldMax 全系列組合 ETF",
      "name_en": "YieldMax Universe Fund",
      "market": "US",
      "currency": "USD",
      "series": "YieldMax",
      "tax_note": "ROC，通常豁免預扣稅",
      "price": 7.82,
      "price_1y_ago": NaN,
      "price_chg_1y": NaN,
      "freq": "weekly",
      "freq_cn": "週息",
      "divs_per_year": 52,
      "recent_div": 0.076,
      "total_div_1y": 5.726,
      "annual_yield": 0.7322,
      "net_1y": NaN,
      "health": "red"
    },
    "YMAG": {
      "name": "YieldMax Mag7 組合 ETF",
      "name_en": "YieldMax Magnificent 7 Fund",
      "market": "US",
      "currency": "USD",
      "series": "YieldMax",
      "tax_note": "ROC，通常豁免預扣稅",
      "price": 11.13,
      "price_1y_ago": NaN,
      "price_chg_1y": NaN,
      "freq": "weekly",
      "freq_cn": "週息",
      "divs_per_year": 52,
      "recent_div": 0.081,
      "total_div_1y": 6.049,
      "annual_yield": 0.5435,
      "net_1y": NaN,
      "health": "red"
    },
    "FEPI": {
      "name": "REX FANG 創新期權收益 ETF",
      "name_en": "REX FANG & Innovation Income ETF",
      "market": "US",
      "currency": "USD",
      "series": "REX",
      "tax_note": "ROC/普通收入混合，部分需扣",
      "price": 41.64,
      "price_1y_ago": 35.8018,
      "price_chg_1y": 0.1631,
      "freq": "weekly",
      "freq_cn": "週息",
      "divs_per_year": 52,
      "recent_div": 0.205,
      "total_div_1y": 10.615,
      "annual_yield": 0.2549,
      "net_1y": 0.418,
      "health": "green"
    },
    "QDTE": {
      "name": "Roundhill S&P500 零日到期收益 ETF",
      "name_en": "Roundhill S&P 500 Zero Days to Expiry",
      "market": "US",
      "currency": "USD",
      "series": "Roundhill",
      "tax_note": "1256 合約收益，部分需扣",
      "price": 30.15,
      "price_1y_ago": NaN,
      "price_chg_1y": NaN,
      "freq": "weekly",
      "freq_cn": "週息",
      "divs_per_year": 52,
      "recent_div": 0.236,
      "total_div_1y": 13.486,
      "annual_yield": 0.4473,
      "net_1y": NaN,
      "health": "red"
    },
    "XDTE": {
      "name": "Roundhill S&P500 週度期權收益 ETF",
      "name_en": "Roundhill S&P 500 Weekly Options",
      "market": "US",
      "currency": "USD",
      "series": "Roundhill",
      "tax_note": "1256 合約收益，部分需扣",
      "price": 38.43,
      "price_1y_ago": NaN,
      "price_chg_1y": NaN,
      "freq": "weekly",
      "freq_cn": "週息",
      "divs_per_year": 52,
      "recent_div": 0.265,
      "total_div_1y": 12.874,
      "annual_yield": 0.335,
      "net_1y": NaN,
      "health": "red"
    },
    "JEPI": {
      "name": "JPMorgan 股票溢價收益 ETF",
      "name_en": "JPMorgan Equity Premium Income",
      "market": "US",
      "currency": "USD",
      "series": "JPMorgan",
      "tax_note": "ELN 結構，部分需扣",
      "price": 56.16,
      "price_1y_ago": 52.2963,
      "price_chg_1y": 0.0739,
      "freq": "monthly",
      "freq_cn": "月息",
      "divs_per_year": 12,
      "recent_div": 0.389,
      "total_div_1y": 4.584,
      "annual_yield": 0.0816,
      "net_1y": 0.1555,
      "health": "green"
    },
    "JEPQ": {
      "name": "JPMorgan 納斯達克溢價收益 ETF",
      "name_en": "JPMorgan Nasdaq Equity Premium Income",
      "market": "US",
      "currency": "USD",
      "series": "JPMorgan",
      "tax_note": "ELN 結構，部分需扣",
      "price": 59.42,
      "price_1y_ago": 48.793,
      "price_chg_1y": 0.2178,
      "freq": "monthly",
      "freq_cn": "月息",
      "divs_per_year": 12,
      "recent_div": 0.564,
      "total_div_1y": 6.12,
      "annual_yield": 0.103,
      "net_1y": 0.3208,
      "health": "green"
    },
    "SPYI": {
      "name": "NEOS S&P500 高收益 ETF",
      "name_en": "NEOS S&P 500 High Income ETF",
      "market": "US",
      "currency": "USD",
      "series": "NEOS",
      "tax_note": "1256 合約，較優惠稅務待遇",
      "price": 51.99,
      "price_1y_ago": 44.5243,
      "price_chg_1y": 0.1677,
      "freq": "monthly",
      "freq_cn": "月息",
      "divs_per_year": 12,
      "recent_div": 0.531,
      "total_div_1y": 6.291,
      "annual_yield": 0.121,
      "net_1y": 0.2887,
      "health": "green"
    },
    "QQQI": {
      "name": "NEOS 納斯達克100 高收益 ETF",
      "name_en": "NEOS Nasdaq-100 High Income ETF",
      "market": "US",
      "currency": "USD",
      "series": "NEOS",
      "tax_note": "1256 合約，較優惠稅務待遇",
      "price": 54.69,
      "price_1y_ago": 44.9806,
      "price_chg_1y": 0.2159,
      "freq": "monthly",
      "freq_cn": "月息",
      "divs_per_year": 12,
      "recent_div": 0.657,
      "total_div_1y": 7.628,
      "annual_yield": 0.1395,
      "net_1y": 0.3554,
      "health": "green"
    },
    "3416.HK": {
      "name": "CSOP 恆生科技每週派息 ETF",
      "name_en": "CSOP HS Tech Weekly Distribution ETF",
      "market": "HK",
      "currency": "HKD",
      "series": "CSOP",
      "tax_note": "港股 ETF，不適用美國預扣稅",
      "price": 8.475,
      "price_1y_ago": 9.0145,
      "price_chg_1y": -0.0598,
      "freq": "monthly",
      "freq_cn": "月息",
      "divs_per_year": 12,
      "recent_div": 0.15,
      "total_div_1y": 1.71,
      "annual_yield": 0.2018,
      "net_1y": 0.142,
      "health": "green"
    }
  }
}