{
  "updated_at": "2026-07-10 13:42 HKT",
  "us": {
    "stocks": [
      {
        "symbol": "MU",
        "price": "$991.6",
        "pct": "+4.52%",
        "dir": "up"
      },
      {
        "symbol": "NVDA",
        "price": "$202.8",
        "pct": "-0.66%",
        "dir": "dn"
      },
      {
        "symbol": "AAPL",
        "price": "$316.2",
        "pct": "+0.90%",
        "dir": "up"
      },
      {
        "symbol": "TSLA",
        "price": "$406.5",
        "pct": "+3.17%",
        "dir": "up"
      },
      {
        "symbol": "SPY",
        "price": "$751.7",
        "pct": "+0.85%",
        "dir": "up"
      }
    ]
  },
  "hk": {
    "stocks": [
      {
        "symbol": "0700.HK",
        "price": "HK$460.2",
        "pct": "-2.00%",
        "dir": "dn"
      },
      {
        "symbol": "1024.HK",
        "price": "HK$43.08",
        "pct": "+2.33%",
        "dir": "up"
      },
      {
        "symbol": "9988.HK",
        "price": "HK$110.4",
        "pct": "+2.22%",
        "dir": "up"
      },
      {
        "symbol": "3690.HK",
        "price": "HK$79.15",
        "pct": "+0.83%",
        "dir": "up"
      },
      {
        "symbol": "1299.HK",
        "price": "HK$73.80",
        "pct": "+2.07%",
        "dir": "up"
      }
    ]
  },
  "tw": {
    "stocks": [
      {
        "symbol": "2330.TW",
        "price": "NT$2,415.0",
        "pct": "+0.00%",
        "dir": "flat"
      },
      {
        "symbol": "2317.TW",
        "price": "NT$237.5",
        "pct": "+0.00%",
        "dir": "flat"
      },
      {
        "symbol": "2454.TW",
        "price": "NT$3,925.0",
        "pct": "+0.00%",
        "dir": "flat"
      },
      {
        "symbol": "2382.TW",
        "price": "NT$373.5",
        "pct": "+0.00%",
        "dir": "flat"
      },
      {
        "symbol": "2308.TW",
        "price": "NT$1,880.0",
        "pct": "+0.00%",
        "dir": "flat"
      }
    ]
  },
  "jp": {
    "stocks": [
      {
        "symbol": "6758.T",
        "price": "¥3,364.0",
        "pct": "-1.32%",
        "dir": "dn"
      },
      {
        "symbol": "7203.T",
        "price": "¥2,824.0",
        "pct": "+0.00%",
        "dir": "flat"
      },
      {
        "symbol": "9984.T",
        "price": "¥6,433.0",
        "pct": "+11.74%",
        "dir": "up"
      },
      {
        "symbol": "7974.T",
        "price": "¥7,012.0",
        "pct": "-1.52%",
        "dir": "dn"
      },
      {
        "symbol": "6501.T",
        "price": "¥4,699.0",
        "pct": "-1.24%",
        "dir": "dn"
      }
    ]
  },
  "crypto": {
    "stocks": [
      {
        "symbol": "BTC",
        "price": "$64,035",
        "pct": "+2.76%",
        "dir": "up"
      },
      {
        "symbol": "ETH",
        "price": "$1,776.1",
        "pct": "+2.03%",
        "dir": "up"
      },
      {
        "symbol": "BNB",
        "price": "$577.2",
        "pct": "+1.24%",
        "dir": "up"
      },
      {
        "symbol": "SOL",
        "price": "$79.17",
        "pct": "+1.68%",
        "dir": "up"
      },
      {
        "symbol": "XRP",
        "price": "$1.11",
        "pct": "+1.47%",
        "dir": "up"
      }
    ]
  }
}